pychunkbuffers/__init__.py
pychunkbuffers-1.0.4.dist-info/LICENSE
pychunkbuffers-1.0.4.dist-info/METADATA
pychunkbuffers-1.0.4.dist-info/WHEEL
pychunkbuffers-1.0.4.dist-info/top_level.txt
pychunkbuffers-1.0.4.dist-info/RECORD
