Metadata-Version: 2.1
Name: pychunkbuffers
Version: 1.0.4
Summary: An open-source python library for writing large amounts of data to buffers via chunks
Home-page: https://github.com/AdityaIyer2k7/pychunkbuffers
Author: AdityaIyer2k7
Author-email: adityaiyer2007@gmail.com
Keywords: python 3,threading,thread,chunking,buffers,pychunk,pybuffer
Classifier: Programming Language :: Python :: 3
Classifier: License :: OSI Approved :: GNU General Public License v3 (GPLv3)
Classifier: Operating System :: OS Independent
Classifier: Topic :: Utilities
Requires-Python: >=3.6
License-File: LICENSE
